{
    "data":[
        {
            "id":"0",
            "firstName":"Andra",
            "lastName":"Scheyer",
            "userName":"AndraScheyer",
            "city":"Washington",
            "department":"D-1"
        },
        {
            "id":"1",
            "firstName":"Candida",
            "lastName":"Corbley",
            "userName":"CandidaCorbley",
            "city":"Atlanta",
            "department":"D-2"
        },
        {
            "id":"2",
            "firstName":"Georgene",
            "lastName":"Montezuma",
            "userName":"GeorgeneMontezuma",
            "city":"Norman",
            "department":"D-3"
        },
        {
            "id":"3",
            "firstName":"Benton",
            "lastName":"Skursky",
            "userName":"BentonSkursky",
            "city":"Garland",
            "department":"D-4"
        },
        {
            "id":"4",
            "firstName":"Stephaine",
            "lastName":"Vinning",
            "userName":"StephaineVinning",
            "city":"Norman",
            "department":"D-5"
        },
        {
            "id":"5",
            "firstName":"Annabelle",
            "lastName":"Boord",
            "userName":"AnnabelleBoord",
            "city":"Seattle",
            "department":"D-1"
        },
        {
            "id":"6",
            "firstName":"Jennifer",
            "lastName":"Fallick",
            "userName":"JenniferFallick",
            "city":"Washington",
            "department":"D-2"
        },
        {
            "id":"7",
            "firstName":"Kerry",
            "lastName":"Theodorov",
            "userName":"KerryTheodorov",
            "city":"Atlanta",
            "department":"D-3"
        },
        {
            "id":"8",
            "firstName":"Chantell",
            "lastName":"Maynerich",
            "userName":"ChantellMaynerich",
            "city":"Norman",
            "department":"D-4"
        },
        {
            "id":"9",
            "firstName":"Ozell",
            "lastName":"Shealy",
            "userName":"OzellShealy",
            "city":"Garland",
            "department":"D-5"
        },
        {
            "id":"10",
            "firstName":"Cheryl",
            "lastName":"Haroldson",
            "userName":"CherylHaroldson",
            "city":"Tampa",
            "department":"D-1"
        },
        {
            "id":"11",
            "firstName":"Audra",
            "lastName":"Kohnert",
            "userName":"AudraKohnert",
            "city":"Seattle",
            "department":"D-2"
        },
        {
            "id":"12",
            "firstName":"Valentin",
            "lastName":"Klimek",
            "userName":"ValentinKlimek",
            "city":"Washington",
            "department":"D-3"
        },
        {
            "id":"13",
            "firstName":"Marti",
            "lastName":"Maybury",
            "userName":"MartiMaybury",
            "city":"Atlanta",
            "department":"D-4"
        },
        {
            "id":"14",
            "firstName":"Thurman",
            "lastName":"Manno",
            "userName":"ThurmanManno",
            "city":"Fargo",
            "department":"D-5"
        },
        {
            "id":"15",
            "firstName":"Kimbery",
            "lastName":"Madarang",
            "userName":"KimberyMadarang",
            "city":"Columbia",
            "department":"D-1"
        },
        {
            "id":"16",
            "firstName":"Rolande",
            "lastName":"Spickerman",
            "userName":"RolandeSpickerman",
            "city":"Tampa",
            "department":"D-2"
        },
        {
            "id":"17",
            "firstName":"Lucina",
            "lastName":"Lary",
            "userName":"LucinaLary",
            "city":"Seattle",
            "department":"D-3"
        },
        {
            "id":"18",
            "firstName":"Van",
            "lastName":"Shire",
            "userName":"VanShire",
            "city":"Washington",
            "department":"D-4"
        },
        {
            "id":"19",
            "firstName":"Rory",
            "lastName":"Papasergi",
            "userName":"RoryPapasergi",
            "city":"Atlanta",
            "department":"D-5"
        },
        {
            "id":"20",
            "firstName":"Herman",
            "lastName":"Demesa",
            "userName":"HermanDemesa",
            "city":"Columbia",
            "department":"D-1"
        },
        {
            "id":"21",
            "firstName":"Oretha",
            "lastName":"Menter",
            "userName":"OrethaMenter",
            "city":"Fargo",
            "department":"D-2"
        },
        {
            "id":"22",
            "firstName":"Brandon",
            "lastName":"Callaro",
            "userName":"BrandonCallaro",
            "city":"Tampa",
            "department":"D-3"
        },
        {
            "id":"23",
            "firstName":"Glory",
            "lastName":"Kulzer",
            "userName":"GloryKulzer",
            "city":"Seattle",
            "department":"D-4"
        },
        {
            "id":"24",
            "firstName":"Estrella",
            "lastName":"Samu",
            "userName":"EstrellaSamu",
            "city":"Washington",
            "department":"D-5"
        }
    ]
}